moonstone/__init__.py
moonstone/main.py
moonstone/version.py
moonstone/analysis/__init__.py
moonstone/analysis/classify.py
moonstone/analysis/clustering.py
moonstone/analysis/columns_statistics.py
moonstone/analysis/differential_analysis.py
moonstone/analysis/randomForest.py
moonstone/analysis/regression.py
moonstone/analysis/statistical_test.py
moonstone/analysis/stats.py
moonstone/analysis/diversity/__init__.py
moonstone/analysis/diversity/alpha.py
moonstone/analysis/diversity/base.py
moonstone/analysis/diversity/beta.py
moonstone/core/__init__.py
moonstone/core/module_base.py
moonstone/filtering/__init__.py
moonstone/filtering/base.py
moonstone/filtering/basics_filtering.py
moonstone/filtering/mean_filtering.py
moonstone/filtering/taxonomy_filtering.py
moonstone/normalization/__init__.py
moonstone/normalization/base.py
moonstone/normalization/counts/__init__.py
moonstone/normalization/counts/geometric_mean.py
moonstone/normalization/counts/random_selection.py
moonstone/normalization/counts/total_counts.py
moonstone/normalization/processed/__init__.py
moonstone/normalization/processed/base.py
moonstone/normalization/processed/scaling_normalization.py
moonstone/normalization/reads/__init__.py
moonstone/normalization/reads/base.py
moonstone/normalization/reads/downsize_dir.py
moonstone/normalization/reads/plot_placeholder.py
moonstone/normalization/reads/read_downsize.py
moonstone/parsers/DataAnalysisType.py
moonstone/parsers/__init__.py
moonstone/parsers/base.py
moonstone/parsers/handleCounts.py
moonstone/parsers/handleMetadata.py
moonstone/parsers/metadata.py
moonstone/parsers/counts/__init__.py
moonstone/parsers/counts/genes.py
moonstone/parsers/counts/picrust2.py
moonstone/parsers/counts/taxonomy/__init__.py
moonstone/parsers/counts/taxonomy/base.py
moonstone/parsers/counts/taxonomy/kraken2.py
moonstone/parsers/counts/taxonomy/metaphlan.py
moonstone/parsers/counts/taxonomy/qiime.py
moonstone/parsers/transform/__init__.py
moonstone/parsers/transform/base.py
moonstone-1.0.0.dist-info/LICENSE
moonstone-1.0.0.dist-info/METADATA
moonstone-1.0.0.dist-info/WHEEL
moonstone-1.0.0.dist-info/entry_points.txt
moonstone-1.0.0.dist-info/top_level.txt
moonstone-1.0.0.dist-info/RECORD
