Metadata-Version: 2.1
Name: moonstone
Version: 1.0.0
Summary: Utilities for metagenomics data analysis using machine learning.
Home-page: UNKNOWN
Author: Kenzo-Hugo Hillion, Agnès Baud, Mariela Furstenheim, Sean Kennedy
Author-email: kehillio@pasteur.fr
License: UNKNOWN
Platform: UNKNOWN
License-File: LICENSE
Requires-Dist: pandas ==2.0.2
Requires-Dist: matplotlib ==3.3.0
Requires-Dist: plotly ==5.17.0
Requires-Dist: statsmodels ==0.13.0
Requires-Dist: python-slugify ==4.0.1
Requires-Dist: pyaml ==20.4.0
Requires-Dist: numpy ==1.24.3
Requires-Dist: scikit-bio ==0.5.9
Requires-Dist: scikit-learn ==1.3.1
Requires-Dist: hdmedians ==0.14.2
Requires-Dist: cython ==0.29.21
Requires-Dist: scipy ==1.9.0
